aderonke_data_structures-0.1.1.dist-info/licenses/LICENSE
data_structures/__init__.py
data_structures/array.py
data_structures/doubly_linked.py
data_structures/graph.py
data_structures/linked_list.py
data_structures/queue.py
data_structures/stack.py
data_structures/tree.py
aderonke_data_structures-0.1.1.dist-info/METADATA
aderonke_data_structures-0.1.1.dist-info/WHEEL
aderonke_data_structures-0.1.1.dist-info/top_level.txt
aderonke_data_structures-0.1.1.dist-info/RECORD
