Metadata-Version: 2.4
Name: aderonke-data-structures
Version: 0.1.1
Summary: This package provides a concise overview of the custom implementations for common data structures in Python
Author: Aderonke Ajefolakemi
Author-email: aajefolakemi@aimsammi.org
License: MIT
Classifier: License :: OSI Approved :: MIT License
Classifier: Programming Language :: Python :: 3
Requires-Python: >=3.6
License-File: LICENSE
Dynamic: author
Dynamic: author-email
Dynamic: classifier
Dynamic: description
Dynamic: description-content-type
Dynamic: license
Dynamic: license-file
Dynamic: requires-python
Dynamic: summary
